pointofpresence/__init__.py
pointofpresence/client_base.py
pointofpresence/delete_organization_method.py
pointofpresence/delete_resource_method.py
pointofpresence/get_kafka_details_method.py
pointofpresence/list_organization_method.py
pointofpresence/register_kafka_method.py
pointofpresence/register_organization_method.py
pointofpresence/register_s3_method.py
pointofpresence/register_url_method.py
pointofpresence/search_method.py
pointofpresence/update_kafka_method.py
pointofpresence/update_s3_method.py
pointofpresence/update_url_method.py
pointofpresence-0.5.2.dist-info/LICENSE
pointofpresence-0.5.2.dist-info/METADATA
pointofpresence-0.5.2.dist-info/WHEEL
pointofpresence-0.5.2.dist-info/top_level.txt
pointofpresence-0.5.2.dist-info/RECORD
