Metadata-Version: 2.2
Name: pointofpresence
Version: 0.5.2
Summary: A Python client library for interacting with the specific API.
Home-page: https://github.com/sci-ndp/pop-py
Author: Raul Bardaji, Saleem Slharir, Andreu Fornos, Philip Davis
Author-email: rbardaji@gmail.com, saleem.alharir@utah.edu, andreu.fornos@utah.edu,philip.davis@sci.utah.edu
Classifier: Programming Language :: Python :: 3
Classifier: License :: OSI Approved :: MIT License
Classifier: Operating System :: OS Independent
Requires-Python: >=3.6
License-File: LICENSE
Requires-Dist: requests
Requires-Dist: pytest
Requires-Dist: coverage
Requires-Dist: codecov
Requires-Dist: flake8
Requires-Dist: pre-commit
Requires-Dist: black
Requires-Dist: build
Requires-Dist: sphinx
Requires-Dist: pytest-asyncio
Dynamic: author
Dynamic: author-email
Dynamic: classifier
Dynamic: description
Dynamic: description-content-type
Dynamic: home-page
Dynamic: requires-dist
Dynamic: requires-python
Dynamic: summary
